{"trades":[{"qty":1656.62650602,"entryPrice":0.00664,"initialStopLoss":0.006308,"stopLoss":0.006308,"takeProfit":0.0074368,"highWaterMark":0.00664,"trailingStopPct":0,"openedAt":"2026-05-29T18:37:57.192Z","currentPrice":0.00664,"symbol":"PIXEL/USDC","side":"SELL","timestamp":"2026-05-29T18:38:08.931Z","exitPrice":0.00664,"pnl":0,"reason":"strategy_sell","balance":33.08,"note":"🔬 smoke-test"},{"qty":1656.62650602,"entryPrice":0.00664,"initialStopLoss":0.006308,"stopLoss":0.006308,"takeProfit":0.0074368,"highWaterMark":0.00664,"trailingStopPct":0,"openedAt":"2026-05-29T18:37:57.192Z","symbol":"PIXEL/USDC","side":"BUY","timestamp":"2026-05-29T18:37:57.192Z","balance":22.08,"note":"🔬 smoke-test","pnl":0},{"qty":56.94585,"entryPrice":0.1758,"initialStopLoss":0,"stopLoss":0,"takeProfit":0,"highWaterMark":0.1758,"openedAt":"2026-05-29T12:54:41.618Z","currentPrice":0.1758,"symbol":"JUP/USDC","side":"SELL","timestamp":"2026-05-29T13:08:03.201Z","exitPrice":0.1758,"pnl":0,"reason":"take_profit","balance":33.08},{"timestamp":"2026-05-29T12:54:41.618Z","symbol":"JUP/USDC","side":"BUY","price":0.1758,"qty":56.94585,"pnl":0,"balance":23.07,"note":"🔄 restored-from-exchange"},{"symbol":"ENA/USDC","side":"BUY","qty":110.44,"entryPrice":0.0997,"stopLoss":0.092721,"takeProfit":0.117646,"timestamp":"2026-05-24T18:38:35.353Z","balance":22.16,"openedAt":"2026-05-24T18:38:35.353Z","note":"🔬 smoke-test","pnl":0},{"symbol":"NEAR/USDC","side":"SELL","entryPrice":2.081,"exitPrice":2.082,"qty":5.19506,"pnl":0.01,"reason":"strategy_sell","timestamp":"2026-05-23T10:50:11.133Z","balance":33.43,"openedAt":"2026-05-23T10:49:44.188Z"},{"symbol":"THETA/USDC","side":"SELL","entryPrice":0.19,"exitPrice":0.189,"qty":58.1898,"pnl":-0.06,"reason":"strategy_sell","timestamp":"2026-05-23T10:50:00.343Z","balance":22.82,"openedAt":"2026-05-23T10:49:47.005Z","note":"🔬 smoke-test"}],"signalFeed":[{"symbol":"JUP/USDC","decision":"HOLD","confidence":2,"timestamp":1780079889967,"reasons":[],"blockReason":null,"strategies":["BB","CCI","OBV"],"triggerHints":["Price touches lower Bollinger Band → BUY · upper band → SELL","CCI crosses above −100 from oversold → BUY · below +100 from overbought → SELL","OBV crosses above EMA-20 → BUY (volume buyers) · crosses below → SELL"]},{"symbol":"ARB/USDC","decision":"HOLD","confidence":0,"timestamp":1780079889933,"reasons":[],"blockReason":null,"strategies":["RSI","WilliamsR","HeikinAshi"],"triggerHints":["RSI < 30 → BUY (oversold) · RSI > 70 → SELL (overbought)","%R < −80 + turning up → BUY (oversold) · %R > −20 + turning down → SELL","HA bullish candle (close>open, no lower wick) → BUY · bearish (no upper wick) → SELL"]},{"symbol":"APT/USDC","decision":"HOLD","confidence":0,"timestamp":1780079890044,"reasons":[],"blockReason":null,"strategies":["BB","Stoch","MFI"],"triggerHints":["Price touches lower Bollinger Band → BUY · upper band → SELL","Stochastic K crosses above D below 20 → BUY · above 80 → SELL","MFI < 20 + turning up → BUY (oversold volume reversal) · MFI > 80 + turning down → SELL"]},{"symbol":"ICP/USDC","decision":"HOLD","confidence":0,"timestamp":1780079890023,"reasons":[],"blockReason":null,"strategies":["RSI","BB","Stoch"],"triggerHints":["RSI < 30 → BUY (oversold) · RSI > 70 → SELL (overbought)","Price touches lower Bollinger Band → BUY · upper band → SELL","Stochastic K crosses above D below 20 → BUY · above 80 → SELL"]},{"symbol":"ENA/USDC","decision":"BUY","confidence":1,"timestamp":1780079890305,"reasons":["bb_buy","cci_buy"],"blockReason":"MTF misaligned (15m: 43% green < 50% required)","strategies":["RSI","BB","CCI"],"triggerHints":["RSI < 30 → BUY (oversold) · RSI > 70 → SELL (overbought)","Price touches lower Bollinger Band → BUY · upper band → SELL","CCI crosses above −100 from oversold → BUY · below +100 from overbought → SELL"]},{"symbol":"RENDER/USDC","decision":"HOLD","confidence":2,"timestamp":1780079889846,"reasons":[],"blockReason":null,"strategies":["EMA","OBV","WilliamsR"],"triggerHints":["Fast EMA crosses above slow EMA → BUY · below → SELL","OBV crosses above EMA-20 → BUY (volume buyers) · crosses below → SELL","%R < −80 + turning up → BUY (oversold) · %R > −20 + turning down → SELL"]},{"symbol":"TON/USDC","decision":"HOLD","confidence":0,"timestamp":1780079889990,"reasons":[],"blockReason":null,"strategies":["EMA","OBV","StochRSI"],"triggerHints":["Fast EMA crosses above slow EMA → BUY · below → SELL","OBV crosses above EMA-20 → BUY (volume buyers) · crosses below → SELL","StochRSI K < 20 crossing up → BUY · K > 80 crossing down → SELL"]},{"symbol":"PEPE/USDC","decision":"HOLD","confidence":0,"timestamp":1780079889868,"reasons":[],"blockReason":null,"strategies":["EMA","Supertrend","OBV"],"triggerHints":["Fast EMA crosses above slow EMA → BUY · below → SELL","Supertrend flips bullish → BUY · flips bearish → SELL","OBV crosses above EMA-20 → BUY (volume buyers) · crosses below → SELL"]},{"symbol":"WLD/USDC","decision":"HOLD","confidence":2,"timestamp":1780079889798,"reasons":[],"blockReason":null,"strategies":["BB","CCI","ADX"],"triggerHints":["Price touches lower Bollinger Band → BUY · upper band → SELL","CCI crosses above −100 from oversold → BUY · below +100 from overbought → SELL","ADX > 25 confirms trend; direction from price vs EMA"]},{"symbol":"ETH/USDC","decision":"HOLD","confidence":2,"timestamp":1780079889782,"reasons":[],"blockReason":null,"strategies":["Supertrend","MFI","SR"],"triggerHints":["Supertrend flips bullish → BUY · flips bearish → SELL","MFI < 20 + turning up → BUY (oversold volume reversal) · MFI > 80 + turning down → SELL","Price near support zone ≥2 touches → BUY · near resistance zone ≥2 touches → SELL"]},{"symbol":"INJ/USDC","decision":"HOLD","confidence":2,"timestamp":1780079889762,"reasons":[],"blockReason":null,"strategies":["ADX","OBV","StochRSI"],"triggerHints":["ADX > 25 confirms trend; direction from price vs EMA","OBV crosses above EMA-20 → BUY (volume buyers) · crosses below → SELL","StochRSI K < 20 crossing up → BUY · K > 80 crossing down → SELL"]},{"symbol":"DOGE/USDC","decision":"HOLD","confidence":0,"timestamp":1780079889842,"reasons":[],"blockReason":null,"strategies":["EMA","PSAR","HeikinAshi"],"triggerHints":["Fast EMA crosses above slow EMA → BUY · below → SELL","Parabolic SAR flips below price → BUY · flips above price → SELL","HA bullish candle (close>open, no lower wick) → BUY · bearish (no upper wick) → SELL"]},{"symbol":"AVAX/USDC","decision":"HOLD","confidence":0,"timestamp":1780079889838,"reasons":[],"blockReason":null,"strategies":["RSI","MACD","PSAR"],"triggerHints":["RSI < 30 → BUY (oversold) · RSI > 70 → SELL (overbought)","MACD line crosses above signal line → BUY · below → SELL","Parabolic SAR flips below price → BUY · flips above price → SELL"]},{"symbol":"ADA/USDC","decision":"HOLD","confidence":2,"timestamp":1780079889817,"reasons":[],"blockReason":null,"strategies":["RSI","BB","CCI"],"triggerHints":["RSI < 30 → BUY (oversold) · RSI > 70 → SELL (overbought)","Price touches lower Bollinger Band → BUY · upper band → SELL","CCI crosses above −100 from oversold → BUY · below +100 from overbought → SELL"]},{"symbol":"SOL/USDC","decision":"HOLD","confidence":0,"timestamp":1780079889791,"reasons":[],"blockReason":null,"strategies":["BB","WilliamsR","StochRSI"],"triggerHints":["Price touches lower Bollinger Band → BUY · upper band → SELL","%R < −80 + turning up → BUY (oversold) · %R > −20 + turning down → SELL","StochRSI K < 20 crossing up → BUY · K > 80 crossing down → SELL"]},{"symbol":"NEAR/USDC","decision":"HOLD","confidence":0,"timestamp":1780079875018,"reasons":[],"strategies":["RSI","BB","Stoch","SR"],"triggerHints":["RSI < 30 → BUY (oversold) · RSI > 70 → SELL (overbought)","Price touches lower Bollinger Band → BUY · upper band → SELL","Stochastic K crosses above D below 20 → BUY · above 80 → SELL","Price near support zone ≥2 touches → BUY · near resistance zone ≥2 touches → SELL"]},{"symbol":"GMX/USDC","decision":"HOLD","confidence":2,"timestamp":1780079890208,"reasons":[],"blockReason":null,"strategies":["RSI","BB","CCI"],"triggerHints":["RSI < 30 → BUY (oversold) · RSI > 70 → SELL (overbought)","Price touches lower Bollinger Band → BUY · upper band → SELL","CCI crosses above −100 from oversold → BUY · below +100 from overbought → SELL"]},{"symbol":"TIA/USDC","decision":"HOLD","confidence":0,"timestamp":1780079889742,"reasons":[],"blockReason":null,"strategies":["CCI","MACD","HeikinAshi"],"triggerHints":["CCI crosses above −100 from oversold → BUY · below +100 from overbought → SELL","MACD line crosses above signal line → BUY · below → SELL","HA bullish candle (close>open, no lower wick) → BUY · bearish (no upper wick) → SELL"]},{"symbol":"THETA/USDC","decision":"HOLD","confidence":2,"timestamp":1780079889734,"reasons":[],"blockReason":null,"strategies":["RSI","CCI","OBV"],"triggerHints":["RSI < 30 → BUY (oversold) · RSI > 70 → SELL (overbought)","CCI crosses above −100 from oversold → BUY · below +100 from overbought → SELL","OBV crosses above EMA-20 → BUY (volume buyers) · crosses below → SELL"]},{"symbol":"VANRY/USDC","decision":"HOLD","confidence":2,"timestamp":1780079889803,"reasons":[],"blockReason":null,"strategies":["EMA","MACD","ADX"],"triggerHints":["Fast EMA crosses above slow EMA → BUY · below → SELL","MACD line crosses above signal line → BUY · below → SELL","ADX > 25 confirms trend; direction from price vs EMA"]},{"symbol":"PAXG/USDC","decision":"HOLD","confidence":0.5,"timestamp":1780079889690,"reasons":[],"blockReason":null,"strategies":["MACD","ADX","Supertrend"],"triggerHints":["MACD line crosses above signal line → BUY · below → SELL","ADX > 25 confirms trend; direction from price vs EMA","Supertrend flips bullish → BUY · flips bearish → SELL"]},{"symbol":"PIXEL/USDC","decision":"HOLD","confidence":2,"timestamp":1780079889715,"reasons":[],"blockReason":null,"strategies":["EMA","ADX","SR"],"triggerHints":["Fast EMA crosses above slow EMA → BUY · below → SELL","ADX > 25 confirms trend; direction from price vs EMA","Price near support zone ≥2 touches → BUY · near resistance zone ≥2 touches → SELL"]},{"symbol":"SUI/USDC","decision":"HOLD","confidence":0,"timestamp":1780079889737,"reasons":[],"blockReason":null,"strategies":["RSI","Stoch","MFI"],"triggerHints":["RSI < 30 → BUY (oversold) · RSI > 70 → SELL (overbought)","Stochastic K crosses above D below 20 → BUY · above 80 → SELL","MFI < 20 + turning up → BUY (oversold volume reversal) · MFI > 80 + turning down → SELL"]},{"symbol":"MANTA/USDC","decision":"HOLD","confidence":0,"timestamp":1780079889688,"reasons":[],"blockReason":null,"strategies":["RSI","BB","CCI"],"triggerHints":["RSI < 30 → BUY (oversold) · RSI > 70 → SELL (overbought)","Price touches lower Bollinger Band → BUY · upper band → SELL","CCI crosses above −100 from oversold → BUY · below +100 from overbought → SELL"]},{"symbol":"LDO/USDC","decision":"HOLD","confidence":0,"timestamp":1780079889646,"reasons":[],"blockReason":null,"strategies":["MACD","ADX","WilliamsR"],"triggerHints":["MACD line crosses above signal line → BUY · below → SELL","ADX > 25 confirms trend; direction from price vs EMA","%R < −80 + turning up → BUY (oversold) · %R > −20 + turning down → SELL"]},{"symbol":"JTO/USDC","decision":"HOLD","confidence":0,"timestamp":1780079889682,"reasons":[],"blockReason":null,"strategies":["CCI","PSAR","SR"],"triggerHints":["CCI crosses above −100 from oversold → BUY · below +100 from overbought → SELL","Parabolic SAR flips below price → BUY · flips above price → SELL","Price near support zone ≥2 touches → BUY · near resistance zone ≥2 touches → SELL"]},{"symbol":"LSK/USDC","decision":"HOLD","confidence":0,"timestamp":1780079889526,"reasons":[],"blockReason":null,"strategies":["MACD","MFI","PSAR"],"triggerHints":["MACD line crosses above signal line → BUY · below → SELL","MFI < 20 + turning up → BUY (oversold volume reversal) · MFI > 80 + turning down → SELL","Parabolic SAR flips below price → BUY · flips above price → SELL"]},{"symbol":"CRV/USDC","decision":"HOLD","confidence":0,"timestamp":1780079875034,"reasons":[],"strategies":["ADX","StochRSI","SR"],"triggerHints":["ADX > 25 confirms trend; direction from price vs EMA","StochRSI K < 20 crossing up → BUY · K > 80 crossing down → SELL","Price near support zone ≥2 touches → BUY · near resistance zone ≥2 touches → SELL"]},{"symbol":"ENS/USDC","decision":"HOLD","confidence":0,"timestamp":1780079889562,"reasons":[],"blockReason":null,"strategies":["BB","PSAR","SR"],"triggerHints":["Price touches lower Bollinger Band → BUY · upper band → SELL","Parabolic SAR flips below price → BUY · flips above price → SELL","Price near support zone ≥2 touches → BUY · near resistance zone ≥2 touches → SELL"]},{"symbol":"BCH/USDC","decision":"HOLD","confidence":2,"timestamp":1780079889493,"reasons":[],"blockReason":null,"strategies":["BB","OBV","WilliamsR"],"triggerHints":["Price touches lower Bollinger Band → BUY · upper band → SELL","OBV crosses above EMA-20 → BUY (volume buyers) · crosses below → SELL","%R < −80 + turning up → BUY (oversold) · %R > −20 + turning down → SELL"]},{"symbol":"ACH/USDC","decision":"HOLD","confidence":2,"timestamp":1780079889504,"reasons":[],"blockReason":null,"strategies":["RSI","BB","CCI"],"triggerHints":["RSI < 30 → BUY (oversold) · RSI > 70 → SELL (overbought)","Price touches lower Bollinger Band → BUY · upper band → SELL","CCI crosses above −100 from oversold → BUY · below +100 from overbought → SELL"]},{"symbol":"TRX/USDC","decision":"HOLD","confidence":0,"timestamp":1780079889481,"reasons":[],"blockReason":null,"strategies":["CCI","Stoch","StochRSI"],"triggerHints":["CCI crosses above −100 from oversold → BUY · below +100 from overbought → SELL","Stochastic K crosses above D below 20 → BUY · above 80 → SELL","StochRSI K < 20 crossing up → BUY · K > 80 crossing down → SELL"]},{"symbol":"LTC/USDC","decision":"HOLD","confidence":0,"timestamp":1780079875014,"reasons":[],"strategies":["BB","EMA","WilliamsR"],"triggerHints":["Price touches lower Bollinger Band → BUY · upper band → SELL","Fast EMA crosses above slow EMA → BUY · below → SELL","%R < −80 + turning up → BUY (oversold) · %R > −20 + turning down → SELL"]},{"symbol":"BNB/USDC","decision":"HOLD","confidence":0,"timestamp":1780079890225,"reasons":[],"blockReason":null,"strategies":["WilliamsR","HeikinAshi","SR"],"triggerHints":["%R < −80 + turning up → BUY (oversold) · %R > −20 + turning down → SELL","HA bullish candle (close>open, no lower wick) → BUY · bearish (no upper wick) → SELL","Price near support zone ≥2 touches → BUY · near resistance zone ≥2 touches → SELL"]},{"symbol":"LINK/USDC","decision":"HOLD","confidence":0,"timestamp":1780079890221,"reasons":[],"blockReason":null,"strategies":["BB","Stoch","Supertrend"],"triggerHints":["Price touches lower Bollinger Band → BUY · upper band → SELL","Stochastic K crosses above D below 20 → BUY · above 80 → SELL","Supertrend flips bullish → BUY · flips bearish → SELL"]},{"symbol":"XRP/USDC","decision":"HOLD","confidence":0,"timestamp":1780079890325,"reasons":[],"blockReason":null,"strategies":["BB","Stoch","EMA"],"triggerHints":["Price touches lower Bollinger Band → BUY · upper band → SELL","Stochastic K crosses above D below 20 → BUY · above 80 → SELL","Fast EMA crosses above slow EMA → BUY · below → SELL"]},{"symbol":"BTC/USDC","decision":"HOLD","confidence":0,"timestamp":1780079889240,"reasons":[],"blockReason":null,"strategies":["EMA","PSAR","HeikinAshi"],"triggerHints":["Fast EMA crosses above slow EMA → BUY · below → SELL","Parabolic SAR flips below price → BUY · flips above price → SELL","HA bullish candle (close>open, no lower wick) → BUY · bearish (no upper wick) → SELL"]}]}